pyPCoA/__init__.py
pyPCoA/core.py
pyPCoA/data/PCoA_BrayCurtis_R.csv
pyPCoA/data/sample_data.csv
pyPCoA-0.1.4.2.dist-info/LICENSE
pyPCoA-0.1.4.2.dist-info/METADATA
pyPCoA-0.1.4.2.dist-info/WHEEL
pyPCoA-0.1.4.2.dist-info/entry_points.txt
pyPCoA-0.1.4.2.dist-info/top_level.txt
pyPCoA-0.1.4.2.dist-info/RECORD
