Metadata-Version: 2.1
Name: pyPCoA
Version: 0.1.4.2
Summary: A Python package for performing PCoA analysis using Jaccard and Bray-Curtis distances.
Home-page: https://github.com/YukiHSun/pyPCoA
Author: Yuki Hamaguchi
Author-email: Yuki Hamaguchi <Yuki_Hamaguchi@suntory.co.jp>
License: MIT License
Keywords: PCoA,Jaccard,Bray-Curtis,Bioinformatics
Classifier: Programming Language :: Python :: 3
Classifier: License :: OSI Approved :: MIT License
Classifier: Operating System :: OS Independent
Requires-Python: >=3.9
License-File: LICENSE
Requires-Dist: numpy
Requires-Dist: pandas
Requires-Dist: matplotlib
